{
  "match_id": "20250111-ballyclare-425e4c3f",
  "veo_url": "https://app.veo.co/matches/20250111-ballyclare-425e4c3f/?highlight=dd5f8812-8e8b-4759-b7b1-cc1d92bd9feb&scroll=MT",
  "extracted_at": "2025-07-28T11:23:38.982033",
  "metadata": {
    "audio_status": null,
    "camera": "14:ae:85:91:65:ed",
    "club": {
      "slug": "newry-city-athletic-football-club",
      "title": "Newry City AFC",
      "permissions": {
        "teams.update_club": {
          "permitted": false,
          "reason": [
            "permission"
          ]
        },
        "teams.update_club_highlight_tags": {
          "permitted": false,
          "reason": [
            "permission"
          ]
        },
        "teams.read_club_highlight_tags": {
          "permitted": false,
          "reason": [
            "permission"
          ]
        }
      },
      "country": {
        "code": "GB",
        "name": "United Kingdom"
      },
      "crest": "https://assets.app.veo.co/crests/newry-city-athletic-football-club/Newry_City_A.F.C.png",
      "short_name": "NC",
      "id": "e213c360-3848-45a9-8d42-3ec3dbc40472",
      "external_id_dbu": null
    },
    "created": "2025-01-11T19:32:55.530293+01:00",
    "duration": 6773,
    "end": "2025-01-11T17:59:17+01:00",
    "expiration_status": "does-not-expire-soon",
    "expires_at": "2026-01-11 18:32:54.773571+00:00",
    "external_id_dbu_club": null,
    "external_id_dbu_match": null,
    "external_id_dbu_pool": null,
    "has_analytics_enabled": false,
    "has_events_enabled": true,
    "has_momentum_data": false,
    "has_playermoments_enabled": false,
    "has_tracking_data": false,
    "id": "ec3ca4f8-1934-4861-b6fa-0a02b7564a0e",
    "identifier": "ec3ca4f8-1934-4861-b6fa-0a02b7564a0e",
    "info": {
      "stats": {
        "score": {
          "own": null,
          "opponent": null
        },
        "score_aggregated": {
          "own": 3,
          "opponent": 1
        },
        "table": [
          "FootballGoal",
          "FootballShot",
          "TotalAttempts",
          "FootballCornerKick",
          "FootballFreeKick",
          "FootballPenaltyKick",
          "PassesCompleted",
          "PossessionPercent",
          "PossessionMinutes",
          "PossessionWon"
        ]
      }
    },
    "is_accessible": true,
    "is_paid_for_storage_minutes": true,
    "is_paid_for_upload_minutes": true,
    "is_shared_recording": false,
    "opponent_club_name": null,
    "opponent_short_name": "",
    "opponent_short_name_display": "",
    "opponent_team_color": "",
    "opponent_team_formation": null,
    "opponent_team_formation_name": "",
    "opponent_team_name": "",
    "own_team_color": "",
    "own_team_formation": null,
    "own_team_formation_name": "",
    "own_team_home_or_away": "home",
    "permissions": {
      "matches.create_match__shareinvitation": {
        "permitted": false,
        "reason": [
          "permission"
        ]
      },
      "matches.destroy_match": {
        "permitted": false,
        "reason": [
          "permission"
        ]
      },
      "matches.download_match": {
        "permitted": false,
        "reason": [
          "permission"
        ]
      },
      "matches.read_match__shareinvitations": {
        "permitted": false,
        "reason": [
          "permission"
        ]
      },
      "matches.update_match": {
        "permitted": false,
        "reason": [
          "permission"
        ]
      },
      "matches.share_match_social": {
        "permitted": true
      },
      "analysis.read_match_analysis": {
        "permitted": false,
        "reason": [
          "permission",
          "entitlement"
        ]
      },
      "analysis.read_match_heatmap": {
        "permitted": false,
        "reason": [
          "permission"
        ]
      },
      "analysis.read_match_momentum": {
        "permitted": false,
        "reason": [
          "permission",
          "entitlement"
        ]
      },
      "analysis.read_match_radar": {
        "permitted": false,
        "reason": [
          "permission",
          "entitlement"
        ]
      },
      "analysis.read_match_stats": {
        "permitted": false,
        "reason": [
          "permission"
        ]
      },
      "analysis.read_match_shotmap": {
        "permitted": false,
        "reason": [
          "permission"
        ]
      },
      "analysis.read_match_passstrings": {
        "permitted": false,
        "reason": [
          "permission"
        ]
      },
      "analysis.read_match_passlocations": {
        "permitted": false,
        "reason": [
          "permission"
        ]
      },
      "analysis.read_match_possessionlocations": {
        "permitted": false,
        "reason": [
          "permission"
        ]
      },
      "analysis.read_match_scoreboard": {
        "permitted": false,
        "reason": [
          "permission",
          "entitlement"
        ]
      },
      "analysis.read_match_formguide": {
        "permitted": false,
        "reason": [
          "permission"
        ]
      },
      "analysis.read_match_playermoments": {
        "permitted": false,
        "reason": [
          "permission",
          "entitlement"
        ]
      },
      "matches.access_zola_admin": {
        "permitted": false,
        "reason": [
          "permission"
        ]
      },
      "matches.create_match_viewcount": {
        "permitted": true
      },
      "matches.create_match__highlight": {
        "permitted": false,
        "reason": [
          "permission"
        ]
      },
      "matches.download_highlight": {
        "permitted": false,
        "reason": [
          "permission"
        ]
      },
      "matches.read_match__periods": {
        "permitted": false,
        "reason": [
          "permission"
        ]
      },
      "matches.read_match_journal": {
        "permitted": false,
        "reason": [
          "permission"
        ]
      },
      "matches.remove_audio_match__videos": {
        "permitted": false,
        "reason": [
          "permission"
        ]
      },
      "matches.resolve_aihighlight": {
        "permitted": false,
        "reason": [
          "permission"
        ]
      },
      "matches.restore_match_video": {
        "permitted": false,
        "reason": [
          "permission"
        ]
      },
      "matches.update_match_journal": {
        "permitted": false,
        "reason": [
          "permission"
        ]
      },
      "matches.read_match__lineup": {
        "permitted": false,
        "reason": [
          "permission"
        ]
      },
      "matches.update_match__lineup": {
        "permitted": false,
        "reason": [
          "permission"
        ]
      },
      "matches.create_match__lineupplayer": {
        "permitted": false,
        "reason": [
          "permission"
        ]
      },
      "matches.read_match__lineupplayer": {
        "permitted": false,
        "reason": [
          "permission"
        ]
      },
      "matches.destroy_match__lineupplayer": {
        "permitted": false,
        "reason": [
          "permission"
        ]
      },
      "matches.create_match_events": {
        "permitted": false,
        "reason": [
          "permission"
        ]
      },
      "matches.read_match_events": {
        "permitted": false,
        "reason": [
          "permission"
        ]
      },
      "matches.update_match_events": {
        "permitted": false,
        "reason": [
          "permission"
        ]
      },
      "matches.destroy_match_events": {
        "permitted": false,
        "reason": [
          "permission"
        ]
      },
      "matches.read_match__video_mode_followcam": {
        "permitted": true
      },
      "matches.read_match__video_mode_interactive": {
        "permitted": true
      },
      "matches.read_match__video_mode_panorama": {
        "permitted": true
      },
      "matches.create_match__highlight_followcam": {
        "permitted": false,
        "reason": [
          "permission"
        ]
      },
      "matches.create_match__highlight_interactivecam": {
        "permitted": false,
        "reason": [
          "permission"
        ]
      },
      "matches.read_match_timeline": {
        "permitted": true
      },
      "matches.access_annotation_tools": {
        "permitted": false,
        "reason": [
          "permission"
        ]
      },
      "matches.read_match__bookmark": {
        "permitted": false,
        "reason": [
          "permission"
        ]
      },
      "matches.update_match__bookmark": {
        "permitted": false,
        "reason": [
          "permission"
        ]
      },
      "matches.destroy_match__bookmark": {
        "permitted": false,
        "reason": [
          "permission"
        ]
      }
    },
    "privacy": "public",
    "processing_status": {},
    "slug": "20250111-ballyclare-425e4c3f",
    "sport": "football",
    "sport_name": "Football",
    "start": "2025-01-11T16:06:20+01:00",
    "tactics": [],
    "team": null,
    "thumbnail": "https://c.veocdn.com/ec3ca4f8-1934-4861-b6fa-0a02b7564a0e/standard/machine/abb5b7e1/thumbnail.jpg",
    "time_to_expiry": {
      "unit": "days",
      "value": 167
    },
    "title": "Ballyclare",
    "type": "",
    "type_name": "",
    "upload_minutes_consumed_on": "2025-01-11T19:32:55.530293+01:00",
    "url": "/matches/20250111-ballyclare-425e4c3f/",
    "view_count": 110
  },
  "events": null,
  "scraped_data": null
}